test_project_987/__init__.py
test_project_987/load.py
test_project_987/maths.py
test_project_987-0.0.0.dist-info/LICENCE
test_project_987-0.0.0.dist-info/METADATA
test_project_987-0.0.0.dist-info/WHEEL
test_project_987-0.0.0.dist-info/top_level.txt
test_project_987-0.0.0.dist-info/RECORD
